.git_archival.txt
.gitattributes
.gitignore
LICENSE
MANIFEST.in
README.md
RELEASING.md
pyproject.toml
setup.cfg
setup.py
.conda/environment.yml
.conda/pylibtiff.recipe/build.sh
.conda/pylibtiff.recipe/meta.yaml
.github/dependabot.yml
.github/workflows/ci.yaml
.github/workflows/deploy-sdist.yaml
libtiff/__init__.py
libtiff/libtiff_ctypes.py
libtiff/lsm.py
libtiff/lzw.py
libtiff/script_options.py
libtiff/test_bittools.py
libtiff/tiff.py
libtiff/tiff_array.py
libtiff/tiff_base.py
libtiff/tiff_channels_and_files.py
libtiff/tiff_data.py
libtiff/tiff_file.py
libtiff/tiff_files.py
libtiff/tiff_h_3_8_2.py
libtiff/tiff_h_3_9_2.py
libtiff/tiff_h_3_9_4.py
libtiff/tiff_h_3_9_5.py
libtiff/tiff_h_4_0_1.py
libtiff/tiff_h_4_0_10.py
libtiff/tiff_h_4_0_2.py
libtiff/tiff_h_4_0_3.py
libtiff/tiff_h_4_0_6.py
libtiff/tiff_h_4_0_7.py
libtiff/tiff_h_4_0_8.py
libtiff/tiff_h_4_0_9.py
libtiff/tiff_h_4_1_0.py
libtiff/tiff_h_4_2_0.py
libtiff/tiff_h_4_3_0.py
libtiff/tiff_h_4_4_0.py
libtiff/tiff_h_4_5_0.py
libtiff/tiff_h_4_5_1.py
libtiff/tiff_h_4_6_0.py
libtiff/tiff_h_4_7_0.py
libtiff/tiff_image.py
libtiff/tiff_sample_plane.py
libtiff/utils.py
libtiff/version.py
libtiff/scripts/__init__.py
libtiff/scripts/convert.py
libtiff/scripts/info.py
libtiff/src/bittools.c
libtiff/src/tif_lzw.c
libtiff/tests/test_libtiff_ctypes.py
libtiff/tests/test_lzw.py
libtiff/tests/test_simple.py
libtiff/tests/test_tiff_array.py
libtiff/tests/test_tiff_file.py
libtiff/tests/test_tiff_image.py
pylibtiff.egg-info/PKG-INFO
pylibtiff.egg-info/SOURCES.txt
pylibtiff.egg-info/dependency_links.txt
pylibtiff.egg-info/entry_points.txt
pylibtiff.egg-info/requires.txt
pylibtiff.egg-info/top_level.txt